yaml_error_report/__init__.py
yaml_error_report/error_report.py
yaml_error_report/formatters.py
yaml_error_report/loader.py
yaml_error_report/types.py
yaml_error_report-0.1.0.dist-info/LICENSE
yaml_error_report-0.1.0.dist-info/METADATA
yaml_error_report-0.1.0.dist-info/WHEEL
yaml_error_report-0.1.0.dist-info/top_level.txt
yaml_error_report-0.1.0.dist-info/RECORD
