Metadata-Version: 2.1
Name: yaml-error-report
Version: 0.1.0
Summary: Create console error reports for YAML (and JSON) documents
Home-page: https://gitlab.com/rmcgregor/yaml-error-report
Author: Robert Mcgregor
Author-email: rmcgregor1990@gmail.com
License: UNKNOWN
Platform: UNKNOWN
Classifier: Development Status :: 3 - Alpha
Classifier: Topic :: Text Processing
Classifier: License :: OSI Approved :: MIT License
Classifier: Programming Language :: Python :: 3.7
Classifier: Programming Language :: Python :: 3.8
Classifier: Operating System :: OS Independent
Requires-Python: >=3.7
Requires-Dist: wrapt
Requires-Dist: termcolor
Requires-Dist: pyyaml
Provides-Extra: test
Requires-Dist: pytest ; extra == 'test'
